Metadata-Version: 2.1
Name: phenom-api-management
Version: 0.0.17
Summary: Phenom Public Apis SDK for Python
Author: phenom
Author-email: api-management@phenom.com
Keywords: resumeparser,search,jobs,candidate,employee,phenom
Classifier: Development Status :: 1 - Planning
Classifier: Intended Audience :: Developers
Classifier: Programming Language :: Python :: 3.6
License-File: LICENSE
Requires-Dist: PyJWT ==2.4.0
Requires-Dist: certifi ==2025.6.15
Requires-Dist: urllib3 ==2.5.0
Requires-Dist: six ==1.16.0
